[
  {
    "category": "Pre-packaged Job Solutions",
    "name": "Account Manager Solution",
    "url": "https://www.shl.com/products/product-catalog/view/account-manager-solution/",
    "remote_testing": "",
    "adaptive_irt": "",
    "test_type": "C\nP\nA\nB",
    "page_number": 1,
    "source": "SHL Catalog"
  },
  {
    "category": "Pre-packaged Job Solutions",
    "name": "Administrative Professional - Short Form",
    "url": "https://www.shl.com/products/product-catalog/view/administrative-professional-short-form/",
    "remote_testing": "",
    "adaptive_irt": "",
    "test_type": "A\nK\nP",
    "page_number": 1,
    "source": "SHL Catalog"
  },
  {
    "category": "Pre-packaged Job Solutions",
    "name": "Agency Manager Solution",
    "url": "https://www.shl.com/products/product-catalog/view/agency-manager-solution/",
    "remote_testing": "",
    "adaptive_irt": "",
    "test_type": "A\nB\nP\nS",
    "page_number": 1,
    "source": "SHL Catalog"
  },
  {
    "category": "Pre-packaged Job Solutions",
    "name": "Apprentice + 8.0 Job Focused Assessment",
    "url": "https://www.shl.com/products/product-catalog/view/apprentice-8-0-job-focused-assessment-4261/",
    "remote_testing": "",
    "adaptive_irt": "",
    "test_type": "B\nP",
    "page_number": 1,
    "source": "SHL Catalog"
  },
  {
    "category": "Pre-packaged Job Solutions",
    "name": "Apprentice 8.0 Job Focused Assessment",
    "url": "https://www.shl.com/products/product-catalog/view/apprentice-8-0-job-focused-assessment/",
    "remote_testing": "",
    "adaptive_irt": "",
    "test_type": "B\nP",
    "page_number": 1,
    "source": "SHL Catalog"
  },
  {
    "category": "Pre-packaged Job Solutions",
    "name": "Bank Administrative Assistant - Short Form",
    "url": "https://www.shl.com/products/product-catalog/view/bank-administrative-assistant-short-form/",
    "remote_testing": "",
    "adaptive_irt": "",
    "test_type": "A\nB\nK\nP",
    "page_number": 1,
    "source": "SHL Catalog"
  },
  {
    "category": "Pre-packaged Job Solutions",
    "name": "Bank Collections Agent - Short Form",
    "url": "https://www.shl.com/products/product-catalog/view/bank-collections-agent-short-form/",
    "remote_testing": "",
    "adaptive_irt": "",
    "test_type": "A\nB\nP",
    "page_number": 1,
    "source": "SHL Catalog"
  },
  {
    "category": "Pre-packaged Job Solutions",
    "name": "Bank Operations Supervisor - Short Form",
    "url": "https://www.shl.com/products/product-catalog/view/bank-operations-supervisor-short-form/",
    "remote_testing": "",
    "adaptive_irt": "",
    "test_type": "A\nB\nP\nS",
    "page_number": 1,
    "source": "SHL Catalog"
  },
  {
    "category": "Pre-packaged Job Solutions",
    "name": "Bilingual Spanish Reservation Agent Solution",
    "url": "https://www.shl.com/products/product-catalog/view/bilingual-spanish-reservation-agent-solution/",
    "remote_testing": "",
    "adaptive_irt": "",
    "test_type": "B\nP\nS\nA",
    "page_number": 1,
    "source": "SHL Catalog"
  },
  {
    "category": "Pre-packaged Job Solutions",
    "name": "Bookkeeping, Accounting, Auditing Clerk Short Form",
    "url": "https://www.shl.com/products/product-catalog/view/bookkeeping-accounting-auditing-clerk-short-form/",
    "remote_testing": "",
    "adaptive_irt": "",
    "test_type": "P\nS\nK\nB\nA",
    "page_number": 1,
    "source": "SHL Catalog"
  },
  {
    "category": "Pre-packaged Job Solutions",
    "name": "Branch Manager - Short Form",
    "url": "https://www.shl.com/products/product-catalog/view/branch-manager-short-form/",
    "remote_testing": "",
    "adaptive_irt": "",
    "test_type": "A\nB\nP",
    "page_number": 1,
    "source": "SHL Catalog"
  },
  {
    "category": "Pre-packaged Job Solutions",
    "name": "Cashier Solution",
    "url": "https://www.shl.com/products/product-catalog/view/cashier-solution/",
    "remote_testing": "",
    "adaptive_irt": "",
    "test_type": "B\nA\nP",
    "page_number": 1,
    "source": "SHL Catalog"
  },
  {
    "category": "Pre-packaged Job Solutions",
    "name": "Claims/Operations Supervisor Solution",
    "url": "https://www.shl.com/products/product-catalog/view/claimsoperations-supervisor-solution/",
    "remote_testing": "",
    "adaptive_irt": "",
    "test_type": "P\nS\nA\nB",
    "page_number": 2,
    "source": "SHL Catalog"
  },
  {
    "category": "Pre-packaged Job Solutions",
    "name": "Contact Center Customer Service + 8.0",
    "url": "https://www.shl.com/products/product-catalog/view/contact-center-customer-service-8-0/",
    "remote_testing": "",
    "adaptive_irt": "",
    "test_type": "A\nB\nC\nP\nS",
    "page_number": 2,
    "source": "SHL Catalog"
  },
  {
    "category": "Pre-packaged Job Solutions",
    "name": "Contact Center Customer Service 8.0",
    "url": "https://www.shl.com/products/product-catalog/view/contact-center-customer-service-8-0-4269/",
    "remote_testing": "",
    "adaptive_irt": "",
    "test_type": "S\nB\nC\nP",
    "page_number": 2,
    "source": "SHL Catalog"
  },
  {
    "category": "Pre-packaged Job Solutions",
    "name": "Contact Center Manager - Short Form",
    "url": "https://www.shl.com/products/product-catalog/view/contact-center-manager-short-form/",
    "remote_testing": "",
    "adaptive_irt": "",
    "test_type": "A\nB\nP\nS",
    "page_number": 2,
    "source": "SHL Catalog"
  },
  {
    "category": "Pre-packaged Job Solutions",
    "name": "Contact Center Sales & Service + 8.0",
    "url": "https://www.shl.com/products/product-catalog/view/contact-center-sales-and-service-8-0/",
    "remote_testing": "",
    "adaptive_irt": "",
    "test_type": "P\nB\nC\nA\nS",
    "page_number": 2,
    "source": "SHL Catalog"
  },
  {
    "category": "Pre-packaged Job Solutions",
    "name": "Contact Center Sales & Service 8.0",
    "url": "https://www.shl.com/products/product-catalog/view/contact-center-sales-and-service-8-0-4268/",
    "remote_testing": "",
    "adaptive_irt": "",
    "test_type": "S\nB\nC\nP",
    "page_number": 2,
    "source": "SHL Catalog"
  },
  {
    "category": "Pre-packaged Job Solutions",
    "name": "Contact Center Team Lead/Coach - Short Form",
    "url": "https://www.shl.com/products/product-catalog/view/contact-center-team-leadcoach-short-form/",
    "remote_testing": "",
    "adaptive_irt": "",
    "test_type": "A\nB\nP\nS",
    "page_number": 2,
    "source": "SHL Catalog"
  },
  {
    "category": "Pre-packaged Job Solutions",
    "name": "Contact Centre Agent Solution - UK",
    "url": "https://www.shl.com/products/product-catalog/view/contact-centre-agent-solution-uk/",
    "remote_testing": "",
    "adaptive_irt": "",
    "test_type": "A\nB\nP\nS",
    "page_number": 2,
    "source": "SHL Catalog"
  },
  {
    "category": "Pre-packaged Job Solutions",
    "name": "Customer Service - Short Form",
    "url": "https://www.shl.com/products/product-catalog/view/customer-service-short-form/",
    "remote_testing": "",
    "adaptive_irt": "",
    "test_type": "A\nB\nP",
    "page_number": 2,
    "source": "SHL Catalog"
  },
  {
    "category": "Pre-packaged Job Solutions",
    "name": "Customer Service - Short Form - UK",
    "url": "https://www.shl.com/products/product-catalog/view/customer-service-short-form-uk/",
    "remote_testing": "",
    "adaptive_irt": "",
    "test_type": "A\nB\nP",
    "page_number": 2,
    "source": "SHL Catalog"
  },
  {
    "category": "Pre-packaged Job Solutions",
    "name": "Customer Service with Sales - Short Form",
    "url": "https://www.shl.com/products/product-catalog/view/customer-service-with-sales-short-form/",
    "remote_testing": "",
    "adaptive_irt": "",
    "test_type": "A\nB\nP",
    "page_number": 2,
    "source": "SHL Catalog"
  },
  {
    "category": "Pre-packaged Job Solutions",
    "name": "Director - Short Form",
    "url": "https://www.shl.com/products/product-catalog/view/director-short-form/",
    "remote_testing": "",
    "adaptive_irt": "",
    "test_type": "A\nB\nP",
    "page_number": 2,
    "source": "SHL Catalog"
  },
  {
    "category": "Pre-packaged Job Solutions",
    "name": "District/Regional Manager Solution",
    "url": "https://www.shl.com/products/product-catalog/view/districtregional-manager-solution/",
    "remote_testing": "",
    "adaptive_irt": "",
    "test_type": "A\nB\nP",
    "page_number": 3,
    "source": "SHL Catalog"
  },
  {
    "category": "Pre-packaged Job Solutions",
    "name": "Entry Level Cashier 7.1 (Americas)",
    "url": "https://www.shl.com/products/product-catalog/view/entry-level-cashier-7-1-%28americas%29/",
    "remote_testing": "",
    "adaptive_irt": "",
    "test_type": "B\nP\nA",
    "page_number": 3,
    "source": "SHL Catalog"
  },
  {
    "category": "Pre-packaged Job Solutions",
    "name": "Entry Level Cashier 7.1 (International)",
    "url": "https://www.shl.com/products/product-catalog/view/entry-level-cashier-7-1-%28international%29/",
    "remote_testing": "",
    "adaptive_irt": "",
    "test_type": "A\nB\nP",
    "page_number": 3,
    "source": "SHL Catalog"
  },
  {
    "category": "Pre-packaged Job Solutions",
    "name": "Entry Level Customer Service 7.1 (Americas)",
    "url": "https://www.shl.com/products/product-catalog/view/entry-level-customer-service-7-1-%28americas%29/",
    "remote_testing": "",
    "adaptive_irt": "",
    "test_type": "C\nP",
    "page_number": 3,
    "source": "SHL Catalog"
  },
  {
    "category": "Pre-packaged Job Solutions",
    "name": "Entry Level Customer Service 7.1 (International)",
    "url": "https://www.shl.com/products/product-catalog/view/entry-level-customer-service-%28retail-and-cc%29-7-1/",
    "remote_testing": "",
    "adaptive_irt": "",
    "test_type": "C\nP",
    "page_number": 3,
    "source": "SHL Catalog"
  },
  {
    "category": "Pre-packaged Job Solutions",
    "name": "Entry Level Customer Service 7.1 (South Africa)",
    "url": "https://www.shl.com/products/product-catalog/view/entry-level-customer-service-7-1-%28south-africa%29/",
    "remote_testing": "",
    "adaptive_irt": "",
    "test_type": "C\nP",
    "page_number": 3,
    "source": "SHL Catalog"
  },
  {
    "category": "Pre-packaged Job Solutions",
    "name": "Entry level Sales 7.1 (Americas)",
    "url": "https://www.shl.com/products/product-catalog/view/entry-level-sales-7-1-%28americas%29/",
    "remote_testing": "",
    "adaptive_irt": "",
    "test_type": "B\nC\nP",
    "page_number": 3,
    "source": "SHL Catalog"
  },
  {
    "category": "Pre-packaged Job Solutions",
    "name": "Entry level Sales 7.1 (International)",
    "url": "https://www.shl.com/products/product-catalog/view/entry-level-sales-7-1/",
    "remote_testing": "",
    "adaptive_irt": "",
    "test_type": "P\nB\nC",
    "page_number": 3,
    "source": "SHL Catalog"
  },
  {
    "category": "Pre-packaged Job Solutions",
    "name": "Entry Level Sales Sift Out 7.1",
    "url": "https://www.shl.com/products/product-catalog/view/entry-level-sales-sift-out-7-1/",
    "remote_testing": "",
    "adaptive_irt": "",
    "test_type": "C\nP\nB",
    "page_number": 3,
    "source": "SHL Catalog"
  },
  {
    "category": "Pre-packaged Job Solutions",
    "name": "Event Sales Manager Solution",
    "url": "https://www.shl.com/products/product-catalog/view/event-sales-manager-solution/",
    "remote_testing": "",
    "adaptive_irt": "",
    "test_type": "S\nA\nB\nP",
    "page_number": 3,
    "source": "SHL Catalog"
  },
  {
    "category": "Pre-packaged Job Solutions",
    "name": "Executive - Short Form",
    "url": "https://www.shl.com/products/product-catalog/view/executive-short-form/",
    "remote_testing": "",
    "adaptive_irt": "",
    "test_type": "A\nB\nP",
    "page_number": 3,
    "source": "SHL Catalog"
  },
  {
    "category": "Pre-packaged Job Solutions",
    "name": "Financial Professional - Short Form",
    "url": "https://www.shl.com/products/product-catalog/view/financial-professional-short-form/",
    "remote_testing": "",
    "adaptive_irt": "",
    "test_type": "A\nB\nP",
    "page_number": 3,
    "source": "SHL Catalog"
  },
  {
    "category": "Pre-packaged Job Solutions",
    "name": "Financial Services Representative Solution",
    "url": "https://www.shl.com/products/product-catalog/view/financial-services-representative-solution/",
    "remote_testing": "",
    "adaptive_irt": "",
    "test_type": "A\nB\nP",
    "page_number": 4,
    "source": "SHL Catalog"
  },
  {
    "category": "Pre-packaged Job Solutions",
    "name": "Front Desk Associate Solution",
    "url": "https://www.shl.com/products/product-catalog/view/front-desk-associate-solution/",
    "remote_testing": "",
    "adaptive_irt": "",
    "test_type": "A\nB\nP",
    "page_number": 4,
    "source": "SHL Catalog"
  },
  {
    "category": "Pre-packaged Job Solutions",
    "name": "Gaming Associate Solution",
    "url": "https://www.shl.com/products/product-catalog/view/gaming-associate-solution/",
    "remote_testing": "",
    "adaptive_irt": "",
    "test_type": "A\nB\nP\nS",
    "page_number": 4,
    "source": "SHL Catalog"
  },
  {
    "category": "Pre-packaged Job Solutions",
    "name": "Gaming Manager Solution",
    "url": "https://www.shl.com/products/product-catalog/view/gaming-manager-solution/",
    "remote_testing": "",
    "adaptive_irt": "",
    "test_type": "S\nA\nB\nK\nP",
    "page_number": 4,
    "source": "SHL Catalog"
  },
  {
    "category": "Pre-packaged Job Solutions",
    "name": "General Entry Level - All Industries 7.0 Solution",
    "url": "https://www.shl.com/products/product-catalog/view/general-entry-level-all-industries-7-0-solution/",
    "remote_testing": "",
    "adaptive_irt": "",
    "test_type": "B",
    "page_number": 4,
    "source": "SHL Catalog"
  },
  {
    "category": "Pre-packaged Job Solutions",
    "name": "General Entry Level - All Industries 7.1 Solution",
    "url": "https://www.shl.com/products/product-catalog/view/general-entry-level-all-industries-7-1-solution/",
    "remote_testing": "",
    "adaptive_irt": "",
    "test_type": "B",
    "page_number": 4,
    "source": "SHL Catalog"
  },
  {
    "category": "Pre-packaged Job Solutions",
    "name": "General Entry Level - All Industries 7.1(Americas)",
    "url": "https://www.shl.com/products/product-catalog/view/general-entry-level-all-industries-7-1%28americas%29/",
    "remote_testing": "",
    "adaptive_irt": "",
    "test_type": "B",
    "page_number": 4,
    "source": "SHL Catalog"
  },
  {
    "category": "Pre-packaged Job Solutions",
    "name": "General Entry Level – Data Entry 7.0 Solution",
    "url": "https://www.shl.com/products/product-catalog/view/general-entry-level-data-entry-7-0-solution/",
    "remote_testing": "",
    "adaptive_irt": "",
    "test_type": "B\nK",
    "page_number": 4,
    "source": "SHL Catalog"
  },
  {
    "category": "Pre-packaged Job Solutions",
    "name": "Graduate + 8.0 Job Focused Assessment",
    "url": "https://www.shl.com/products/product-catalog/view/graduate-8-0-job-focused-assessment/",
    "remote_testing": "",
    "adaptive_irt": "",
    "test_type": "A\nB\nP",
    "page_number": 4,
    "source": "SHL Catalog"
  },
  {
    "category": "Pre-packaged Job Solutions",
    "name": "Graduate 7.1 Job Focused Assessment",
    "url": "https://www.shl.com/products/product-catalog/view/graduate-7-1-job-focused-assessment/",
    "remote_testing": "",
    "adaptive_irt": "",
    "test_type": "B\nC",
    "page_number": 4,
    "source": "SHL Catalog"
  },
  {
    "category": "Pre-packaged Job Solutions",
    "name": "Graduate 8.0 Job Focused Assessment",
    "url": "https://www.shl.com/products/product-catalog/view/graduate-8-0-job-focused-assessment-4228/",
    "remote_testing": "",
    "adaptive_irt": "",
    "test_type": "P\nB",
    "page_number": 4,
    "source": "SHL Catalog"
  },
  {
    "category": "Pre-packaged Job Solutions",
    "name": "Guest Service Team 7.0 Solution",
    "url": "https://www.shl.com/products/product-catalog/view/guest-service-team-7-0-solution/",
    "remote_testing": "",
    "adaptive_irt": "",
    "test_type": "B",
    "page_number": 4,
    "source": "SHL Catalog"
  },
  {
    "category": "Pre-packaged Job Solutions",
    "name": "Guest Services Associate Solution",
    "url": "https://www.shl.com/products/product-catalog/view/guest-services-associate-solution/",
    "remote_testing": "",
    "adaptive_irt": "",
    "test_type": "A\nB\nP\nS",
    "page_number": 5,
    "source": "SHL Catalog"
  },
  {
    "category": "Pre-packaged Job Solutions",
    "name": "Healthcare Aide 7.0 Solution",
    "url": "https://www.shl.com/products/product-catalog/view/healthcare-aide-7-0-solution/",
    "remote_testing": "",
    "adaptive_irt": "",
    "test_type": "B",
    "page_number": 5,
    "source": "SHL Catalog"
  },
  {
    "category": "Pre-packaged Job Solutions",
    "name": "Healthcare Call Center Agent Solution",
    "url": "https://www.shl.com/products/product-catalog/view/healthcare-call-center-agent-solution/",
    "remote_testing": "",
    "adaptive_irt": "",
    "test_type": "A\nB\nP\nS",
    "page_number": 5,
    "source": "SHL Catalog"
  },
  {
    "category": "Pre-packaged Job Solutions",
    "name": "Healthcare Service Associate Solution",
    "url": "https://www.shl.com/products/product-catalog/view/healthcare-service-associate-solution/",
    "remote_testing": "",
    "adaptive_irt": "",
    "test_type": "A\nB\nP",
    "page_number": 5,
    "source": "SHL Catalog"
  },
  {
    "category": "Pre-packaged Job Solutions",
    "name": "Healthcare Support Specialist Solution",
    "url": "https://www.shl.com/products/product-catalog/view/healthcare-support-specialist-solution/",
    "remote_testing": "",
    "adaptive_irt": "",
    "test_type": "A\nB\nP",
    "page_number": 5,
    "source": "SHL Catalog"
  },
  {
    "category": "Pre-packaged Job Solutions",
    "name": "Home Health Aide Solution",
    "url": "https://www.shl.com/products/product-catalog/view/home-health-aide-solution/",
    "remote_testing": "",
    "adaptive_irt": "",
    "test_type": "A\nB\nP",
    "page_number": 5,
    "source": "SHL Catalog"
  },
  {
    "category": "Pre-packaged Job Solutions",
    "name": "Hospitality Manager Solution",
    "url": "https://www.shl.com/products/product-catalog/view/hospitality-manager-solution/",
    "remote_testing": "",
    "adaptive_irt": "",
    "test_type": "A\nB\nK\nP",
    "page_number": 5,
    "source": "SHL Catalog"
  },
  {
    "category": "Pre-packaged Job Solutions",
    "name": "Host Solution",
    "url": "https://www.shl.com/products/product-catalog/view/host-solution/",
    "remote_testing": "",
    "adaptive_irt": "",
    "test_type": "B\nP",
    "page_number": 5,
    "source": "SHL Catalog"
  },
  {
    "category": "Pre-packaged Job Solutions",
    "name": "Industrial - Entry Level 7.0 Solution",
    "url": "https://www.shl.com/products/product-catalog/view/industrial-entry-level-7-0-solution/",
    "remote_testing": "",
    "adaptive_irt": "",
    "test_type": "B",
    "page_number": 5,
    "source": "SHL Catalog"
  },
  {
    "category": "Pre-packaged Job Solutions",
    "name": "Industrial - Entry Level 7.1 (Americas)",
    "url": "https://www.shl.com/products/product-catalog/view/industrial-entry-level-7-1-%28americas%29/",
    "remote_testing": "",
    "adaptive_irt": "",
    "test_type": "B",
    "page_number": 5,
    "source": "SHL Catalog"
  },
  {
    "category": "Pre-packaged Job Solutions",
    "name": "Industrial - Entry Level 7.1 (International)",
    "url": "https://www.shl.com/products/product-catalog/view/industrial-entry-level-7-1-%28international%29/",
    "remote_testing": "",
    "adaptive_irt": "",
    "test_type": "B",
    "page_number": 5,
    "source": "SHL Catalog"
  },
  {
    "category": "Pre-packaged Job Solutions",
    "name": "Industrial - Professional and Skilled 7.0 Solution",
    "url": "https://www.shl.com/products/product-catalog/view/industrial-professional-and-skilled-7-0-solution/",
    "remote_testing": "",
    "adaptive_irt": "",
    "test_type": "A\nB",
    "page_number": 5,
    "source": "SHL Catalog"
  },
  {
    "category": "Pre-packaged Job Solutions",
    "name": "Industrial - Semi-skilled 7.1 (Americas)",
    "url": "https://www.shl.com/products/product-catalog/view/industrial-semi-skilled-7-1-%28americas%29/",
    "remote_testing": "",
    "adaptive_irt": "",
    "test_type": "B",
    "page_number": 6,
    "source": "SHL Catalog"
  },
  {
    "category": "Pre-packaged Job Solutions",
    "name": "Industrial - Semi-skilled 7.1 (International)",
    "url": "https://www.shl.com/products/product-catalog/view/industrial-semi-skilled-7-1-%28international%29/",
    "remote_testing": "",
    "adaptive_irt": "",
    "test_type": "B",
    "page_number": 6,
    "source": "SHL Catalog"
  },
  {
    "category": "Pre-packaged Job Solutions",
    "name": "Industrial Professional and Skilled 7.1 (Americas)",
    "url": "https://www.shl.com/products/product-catalog/view/industrial-professional-and-skilled-7-1-%28americas%29/",
    "remote_testing": "",
    "adaptive_irt": "",
    "test_type": "A\nB",
    "page_number": 6,
    "source": "SHL Catalog"
  },
  {
    "category": "Pre-packaged Job Solutions",
    "name": "Industrial Professional and Skilled 7.1 Solution",
    "url": "https://www.shl.com/products/product-catalog/view/industrial-professional-and-skilled-7-1-solution/",
    "remote_testing": "",
    "adaptive_irt": "",
    "test_type": "A\nB",
    "page_number": 6,
    "source": "SHL Catalog"
  },
  {
    "category": "Pre-packaged Job Solutions",
    "name": "Installation and Repair Technician Solution",
    "url": "https://www.shl.com/products/product-catalog/view/installation-and-repair-technician-solution/",
    "remote_testing": "",
    "adaptive_irt": "",
    "test_type": "A\nB\nP\nS",
    "page_number": 6,
    "source": "SHL Catalog"
  },
  {
    "category": "Pre-packaged Job Solutions",
    "name": "Insurance Account Manager Solution",
    "url": "https://www.shl.com/products/product-catalog/view/insurance-account-manager-solution/",
    "remote_testing": "",
    "adaptive_irt": "",
    "test_type": "A\nB\nP\nS",
    "page_number": 6,
    "source": "SHL Catalog"
  },
  {
    "category": "Pre-packaged Job Solutions",
    "name": "Insurance Administrative Assistant Solution",
    "url": "https://www.shl.com/products/product-catalog/view/insurance-administrative-assistant-solution/",
    "remote_testing": "",
    "adaptive_irt": "",
    "test_type": "A\nB\nP\nS",
    "page_number": 6,
    "source": "SHL Catalog"
  },
  {
    "category": "Pre-packaged Job Solutions",
    "name": "Insurance Agent Solution",
    "url": "https://www.shl.com/products/product-catalog/view/insurance-agent-solution/",
    "remote_testing": "",
    "adaptive_irt": "",
    "test_type": "A\nB\nP",
    "page_number": 6,
    "source": "SHL Catalog"
  },
  {
    "category": "Pre-packaged Job Solutions",
    "name": "Insurance Director Solution",
    "url": "https://www.shl.com/products/product-catalog/view/insurance-director-solution/",
    "remote_testing": "",
    "adaptive_irt": "",
    "test_type": "A\nB\nP",
    "page_number": 6,
    "source": "SHL Catalog"
  },
  {
    "category": "Pre-packaged Job Solutions",
    "name": "Insurance Sales Manager Solution",
    "url": "https://www.shl.com/products/product-catalog/view/insurance-sales-manager-solution/",
    "remote_testing": "",
    "adaptive_irt": "",
    "test_type": "A\nB\nP\nS",
    "page_number": 6,
    "source": "SHL Catalog"
  },
  {
    "category": "Pre-packaged Job Solutions",
    "name": "Manager - Short Form",
    "url": "https://www.shl.com/products/product-catalog/view/manager-short-form/",
    "remote_testing": "",
    "adaptive_irt": "",
    "test_type": "A\nB\nK\nP\nS",
    "page_number": 6,
    "source": "SHL Catalog"
  },
  {
    "category": "Pre-packaged Job Solutions",
    "name": "Manager + 7.0 Solution",
    "url": "https://www.shl.com/products/product-catalog/view/manager-7-0-solution-3955/",
    "remote_testing": "",
    "adaptive_irt": "",
    "test_type": "A\nB\nC",
    "page_number": 6,
    "source": "SHL Catalog"
  },
  {
    "category": "Pre-packaged Job Solutions",
    "name": "Manager + 7.1 (Americas)",
    "url": "https://www.shl.com/products/product-catalog/view/manager-7-1-solution-4242/",
    "remote_testing": "",
    "adaptive_irt": "",
    "test_type": "B\nC\nP",
    "page_number": 7,
    "source": "SHL Catalog"
  },
  {
    "category": "Pre-packaged Job Solutions",
    "name": "Manager + 7.1 (International)",
    "url": "https://www.shl.com/products/product-catalog/view/manager-7-1-%28international%29/",
    "remote_testing": "",
    "adaptive_irt": "",
    "test_type": "B\nC\nP",
    "page_number": 7,
    "source": "SHL Catalog"
  },
  {
    "category": "Pre-packaged Job Solutions",
    "name": "Manager 7.0 Solution",
    "url": "https://www.shl.com/products/product-catalog/view/manager-7-0-solution/",
    "remote_testing": "",
    "adaptive_irt": "",
    "test_type": "B\nC",
    "page_number": 7,
    "source": "SHL Catalog"
  },
  {
    "category": "Pre-packaged Job Solutions",
    "name": "Manager 7.1 (Americas)",
    "url": "https://www.shl.com/products/product-catalog/view/manager-7-1-%28americas%29/",
    "remote_testing": "",
    "adaptive_irt": "",
    "test_type": "B\nC\nP",
    "page_number": 7,
    "source": "SHL Catalog"
  },
  {
    "category": "Pre-packaged Job Solutions",
    "name": "Manager 7.1 (International)",
    "url": "https://www.shl.com/products/product-catalog/view/manager-7-1-solution/",
    "remote_testing": "",
    "adaptive_irt": "",
    "test_type": "B\nC\nP",
    "page_number": 7,
    "source": "SHL Catalog"
  },
  {
    "category": "Pre-packaged Job Solutions",
    "name": "Manager 8.0 JFA",
    "url": "https://www.shl.com/products/product-catalog/view/manager-8-0-jfa/",
    "remote_testing": "",
    "adaptive_irt": "",
    "test_type": "B\nK\nP",
    "page_number": 7,
    "source": "SHL Catalog"
  },
  {
    "category": "Pre-packaged Job Solutions",
    "name": "Manager 8.0+ JFA",
    "url": "https://www.shl.com/products/product-catalog/view/manager-8-0-jfa-4310/",
    "remote_testing": "",
    "adaptive_irt": "",
    "test_type": "B\nK\nP",
    "page_number": 7,
    "source": "SHL Catalog"
  },
  {
    "category": "Pre-packaged Job Solutions",
    "name": "Manufacturing Production Team Member",
    "url": "https://www.shl.com/products/product-catalog/view/manufacturing-production-team-member/",
    "remote_testing": "",
    "adaptive_irt": "",
    "test_type": "A\nB",
    "page_number": 7,
    "source": "SHL Catalog"
  },
  {
    "category": "Pre-packaged Job Solutions",
    "name": "Manufacturing Skilled Maintenance Worker",
    "url": "https://www.shl.com/products/product-catalog/view/manufacturing-skilled-maintenance-worker/",
    "remote_testing": "",
    "adaptive_irt": "",
    "test_type": "A\nB",
    "page_number": 7,
    "source": "SHL Catalog"
  },
  {
    "category": "Pre-packaged Job Solutions",
    "name": "Network Engineer/Analyst Solution",
    "url": "https://www.shl.com/products/product-catalog/view/network-engineeranalyst-solution/",
    "remote_testing": "",
    "adaptive_irt": "",
    "test_type": "P\nS\nK\nB\nA",
    "page_number": 7,
    "source": "SHL Catalog"
  },
  {
    "category": "Pre-packaged Job Solutions",
    "name": "Nurse Leader Solution",
    "url": "https://www.shl.com/products/product-catalog/view/nurse-leader-solution/",
    "remote_testing": "",
    "adaptive_irt": "",
    "test_type": "S\nA\nB\nP",
    "page_number": 7,
    "source": "SHL Catalog"
  },
  {
    "category": "Pre-packaged Job Solutions",
    "name": "Nurse Solution",
    "url": "https://www.shl.com/products/product-catalog/view/nurse-solution/",
    "remote_testing": "",
    "adaptive_irt": "",
    "test_type": "P\nA\nB",
    "page_number": 7,
    "source": "SHL Catalog"
  },
  {
    "category": "Pre-packaged Job Solutions",
    "name": "Nursing Assistant Solution",
    "url": "https://www.shl.com/products/product-catalog/view/nursing-assistant-solution/",
    "remote_testing": "",
    "adaptive_irt": "",
    "test_type": "A\nB\nP",
    "page_number": 8,
    "source": "SHL Catalog"
  },
  {
    "category": "Pre-packaged Job Solutions",
    "name": "Personal Banker - Short Form",
    "url": "https://www.shl.com/products/product-catalog/view/personal-banker-short-form/",
    "remote_testing": "",
    "adaptive_irt": "",
    "test_type": "A\nB\nK\nP\nS",
    "page_number": 8,
    "source": "SHL Catalog"
  },
  {
    "category": "Pre-packaged Job Solutions",
    "name": "Phone Banker - Short Form",
    "url": "https://www.shl.com/products/product-catalog/view/phone-banker-short-form/",
    "remote_testing": "",
    "adaptive_irt": "",
    "test_type": "A\nB\nP",
    "page_number": 8,
    "source": "SHL Catalog"
  },
  {
    "category": "Pre-packaged Job Solutions",
    "name": "Prep/Line Cook Solution",
    "url": "https://www.shl.com/products/product-catalog/view/prepline-cook-solution/",
    "remote_testing": "",
    "adaptive_irt": "",
    "test_type": "A\nB\nP",
    "page_number": 8,
    "source": "SHL Catalog"
  },
  {
    "category": "Pre-packaged Job Solutions",
    "name": "Professional + 7.0 Solution",
    "url": "https://www.shl.com/products/product-catalog/view/professional-7-0-solution-3958/",
    "remote_testing": "",
    "adaptive_irt": "",
    "test_type": "A\nB\nC",
    "page_number": 8,
    "source": "SHL Catalog"
  },
  {
    "category": "Pre-packaged Job Solutions",
    "name": "Professional + 7.1 (Americas)",
    "url": "https://www.shl.com/products/product-catalog/view/professional-7-1-%28americas%29/",
    "remote_testing": "",
    "adaptive_irt": "",
    "test_type": "B\nC\nP",
    "page_number": 8,
    "source": "SHL Catalog"
  },
  {
    "category": "Pre-packaged Job Solutions",
    "name": "Professional + 7.1 (International)",
    "url": "https://www.shl.com/products/product-catalog/view/professional-7-1-solution/",
    "remote_testing": "",
    "adaptive_irt": "",
    "test_type": "B\nC\nP",
    "page_number": 8,
    "source": "SHL Catalog"
  },
  {
    "category": "Pre-packaged Job Solutions",
    "name": "Professional 7.0 Solution",
    "url": "https://www.shl.com/products/product-catalog/view/professional-7-0-solution/",
    "remote_testing": "",
    "adaptive_irt": "",
    "test_type": "B\nC",
    "page_number": 8,
    "source": "SHL Catalog"
  },
  {
    "category": "Pre-packaged Job Solutions",
    "name": "Professional 7.1 (International)",
    "url": "https://www.shl.com/products/product-catalog/view/professional-7-1-solution-4247/",
    "remote_testing": "",
    "adaptive_irt": "",
    "test_type": "C\nB",
    "page_number": 8,
    "source": "SHL Catalog"
  },
  {
    "category": "Pre-packaged Job Solutions",
    "name": "Professional 8.0 JFA",
    "url": "https://www.shl.com/products/product-catalog/view/professional-8-0-jfa/",
    "remote_testing": "",
    "adaptive_irt": "",
    "test_type": "B\nK\nP",
    "page_number": 8,
    "source": "SHL Catalog"
  },
  {
    "category": "Pre-packaged Job Solutions",
    "name": "Professional/Individual Contributor - Short Form",
    "url": "https://www.shl.com/products/product-catalog/view/professionalindividual-contributor-short-form/",
    "remote_testing": "",
    "adaptive_irt": "",
    "test_type": "A\nB\nP\nS",
    "page_number": 8,
    "source": "SHL Catalog"
  },
  {
    "category": "Pre-packaged Job Solutions",
    "name": "Project Manager - Short Form",
    "url": "https://www.shl.com/products/product-catalog/view/project-manager-short-form/",
    "remote_testing": "",
    "adaptive_irt": "",
    "test_type": "A\nB\nP\nS",
    "page_number": 8,
    "source": "SHL Catalog"
  },
  {
    "category": "Pre-packaged Job Solutions",
    "name": "Proof Operator - Processing Specialist -Short Form",
    "url": "https://www.shl.com/products/product-catalog/view/proof-operator-processing-specialist-short-form/",
    "remote_testing": "",
    "adaptive_irt": "",
    "test_type": "S",
    "page_number": 9,
    "source": "SHL Catalog"
  },
  {
    "category": "Pre-packaged Job Solutions",
    "name": "Reservation Agent Solution",
    "url": "https://www.shl.com/products/product-catalog/view/reservation-agent-solution/",
    "remote_testing": "",
    "adaptive_irt": "",
    "test_type": "A\nP\nS\nB",
    "page_number": 9,
    "source": "SHL Catalog"
  },
  {
    "category": "Pre-packaged Job Solutions",
    "name": "Restaurant Manager Solution",
    "url": "https://www.shl.com/products/product-catalog/view/restaurant-manager-solution/",
    "remote_testing": "",
    "adaptive_irt": "",
    "test_type": "A\nB\nP\nS",
    "page_number": 9,
    "source": "SHL Catalog"
  },
  {
    "category": "Pre-packaged Job Solutions",
    "name": "Restaurant Supervisor Solution",
    "url": "https://www.shl.com/products/product-catalog/view/restaurant-supervisor-solution/",
    "remote_testing": "",
    "adaptive_irt": "",
    "test_type": "A\nB\nP",
    "page_number": 9,
    "source": "SHL Catalog"
  },
  {
    "category": "Pre-packaged Job Solutions",
    "name": "Retail Consultant Solution",
    "url": "https://www.shl.com/products/product-catalog/view/retail-consultant-solution/",
    "remote_testing": "",
    "adaptive_irt": "",
    "test_type": "A\nB\nP",
    "page_number": 9,
    "source": "SHL Catalog"
  },
  {
    "category": "Pre-packaged Job Solutions",
    "name": "Retail Manager w/ Sales Solution",
    "url": "https://www.shl.com/products/product-catalog/view/retail-manager-w-sales-solution/",
    "remote_testing": "",
    "adaptive_irt": "",
    "test_type": "A\nB\nP",
    "page_number": 9,
    "source": "SHL Catalog"
  },
  {
    "category": "Pre-packaged Job Solutions",
    "name": "Retail Sales Associate Solution",
    "url": "https://www.shl.com/products/product-catalog/view/retail-sales-associate-solution/",
    "remote_testing": "",
    "adaptive_irt": "",
    "test_type": "A\nB\nP",
    "page_number": 9,
    "source": "SHL Catalog"
  },
  {
    "category": "Pre-packaged Job Solutions",
    "name": "Sales Director Solution",
    "url": "https://www.shl.com/products/product-catalog/view/sales-director-solution/",
    "remote_testing": "",
    "adaptive_irt": "",
    "test_type": "A\nB\nP",
    "page_number": 9,
    "source": "SHL Catalog"
  },
  {
    "category": "Pre-packaged Job Solutions",
    "name": "Sales Engineer Solution",
    "url": "https://www.shl.com/products/product-catalog/view/sales-engineer-solution/",
    "remote_testing": "",
    "adaptive_irt": "",
    "test_type": "A\nB\nK\nP\nS",
    "page_number": 9,
    "source": "SHL Catalog"
  },
  {
    "category": "Pre-packaged Job Solutions",
    "name": "Sales Manager Solution",
    "url": "https://www.shl.com/products/product-catalog/view/sales-manager-solution/",
    "remote_testing": "",
    "adaptive_irt": "",
    "test_type": "A\nB\nP",
    "page_number": 9,
    "source": "SHL Catalog"
  },
  {
    "category": "Pre-packaged Job Solutions",
    "name": "Sales Professional 7.0 Solution",
    "url": "https://www.shl.com/products/product-catalog/view/sales-professional-7-0-solution/",
    "remote_testing": "",
    "adaptive_irt": "",
    "test_type": "C\nB",
    "page_number": 9,
    "source": "SHL Catalog"
  },
  {
    "category": "Pre-packaged Job Solutions",
    "name": "Sales Professional 7.1 (Americas)",
    "url": "https://www.shl.com/products/product-catalog/view/sales-professional-7-1-%28americas%29/",
    "remote_testing": "",
    "adaptive_irt": "",
    "test_type": "B\nC",
    "page_number": 9,
    "source": "SHL Catalog"
  },
  {
    "category": "Pre-packaged Job Solutions",
    "name": "Proof Operator - Processing Specialist -Short Form",
    "url": "https://www.shl.com/products/product-catalog/view/proof-operator-processing-specialist-short-form/",
    "remote_testing": "",
    "adaptive_irt": "",
    "test_type": "S",
    "page_number": 10,
    "source": "SHL Catalog"
  },
  {
    "category": "Pre-packaged Job Solutions",
    "name": "Reservation Agent Solution",
    "url": "https://www.shl.com/products/product-catalog/view/reservation-agent-solution/",
    "remote_testing": "",
    "adaptive_irt": "",
    "test_type": "A\nP\nS\nB",
    "page_number": 10,
    "source": "SHL Catalog"
  },
  {
    "category": "Pre-packaged Job Solutions",
    "name": "Restaurant Manager Solution",
    "url": "https://www.shl.com/products/product-catalog/view/restaurant-manager-solution/",
    "remote_testing": "",
    "adaptive_irt": "",
    "test_type": "A\nB\nP\nS",
    "page_number": 10,
    "source": "SHL Catalog"
  },
  {
    "category": "Pre-packaged Job Solutions",
    "name": "Restaurant Supervisor Solution",
    "url": "https://www.shl.com/products/product-catalog/view/restaurant-supervisor-solution/",
    "remote_testing": "",
    "adaptive_irt": "",
    "test_type": "A\nB\nP",
    "page_number": 10,
    "source": "SHL Catalog"
  },
  {
    "category": "Pre-packaged Job Solutions",
    "name": "Retail Consultant Solution",
    "url": "https://www.shl.com/products/product-catalog/view/retail-consultant-solution/",
    "remote_testing": "",
    "adaptive_irt": "",
    "test_type": "A\nB\nP",
    "page_number": 10,
    "source": "SHL Catalog"
  },
  {
    "category": "Pre-packaged Job Solutions",
    "name": "Retail Manager w/ Sales Solution",
    "url": "https://www.shl.com/products/product-catalog/view/retail-manager-w-sales-solution/",
    "remote_testing": "",
    "adaptive_irt": "",
    "test_type": "A\nB\nP",
    "page_number": 10,
    "source": "SHL Catalog"
  },
  {
    "category": "Pre-packaged Job Solutions",
    "name": "Retail Sales Associate Solution",
    "url": "https://www.shl.com/products/product-catalog/view/retail-sales-associate-solution/",
    "remote_testing": "",
    "adaptive_irt": "",
    "test_type": "A\nB\nP",
    "page_number": 10,
    "source": "SHL Catalog"
  },
  {
    "category": "Pre-packaged Job Solutions",
    "name": "Sales Director Solution",
    "url": "https://www.shl.com/products/product-catalog/view/sales-director-solution/",
    "remote_testing": "",
    "adaptive_irt": "",
    "test_type": "A\nB\nP",
    "page_number": 10,
    "source": "SHL Catalog"
  },
  {
    "category": "Pre-packaged Job Solutions",
    "name": "Sales Engineer Solution",
    "url": "https://www.shl.com/products/product-catalog/view/sales-engineer-solution/",
    "remote_testing": "",
    "adaptive_irt": "",
    "test_type": "A\nB\nK\nP\nS",
    "page_number": 10,
    "source": "SHL Catalog"
  },
  {
    "category": "Pre-packaged Job Solutions",
    "name": "Sales Manager Solution",
    "url": "https://www.shl.com/products/product-catalog/view/sales-manager-solution/",
    "remote_testing": "",
    "adaptive_irt": "",
    "test_type": "A\nB\nP",
    "page_number": 10,
    "source": "SHL Catalog"
  },
  {
    "category": "Pre-packaged Job Solutions",
    "name": "Sales Professional 7.0 Solution",
    "url": "https://www.shl.com/products/product-catalog/view/sales-professional-7-0-solution/",
    "remote_testing": "",
    "adaptive_irt": "",
    "test_type": "C\nB",
    "page_number": 10,
    "source": "SHL Catalog"
  },
  {
    "category": "Pre-packaged Job Solutions",
    "name": "Sales Professional 7.1 (Americas)",
    "url": "https://www.shl.com/products/product-catalog/view/sales-professional-7-1-%28americas%29/",
    "remote_testing": "",
    "adaptive_irt": "",
    "test_type": "B\nC",
    "page_number": 10,
    "source": "SHL Catalog"
  },
  {
    "category": "Pre-packaged Job Solutions",
    "name": "Sales Professional Solution",
    "url": "https://www.shl.com/products/product-catalog/view/sales-professional-solution/",
    "remote_testing": "",
    "adaptive_irt": "",
    "test_type": "A\nB\nP",
    "page_number": 11,
    "source": "SHL Catalog"
  },
  {
    "category": "Pre-packaged Job Solutions",
    "name": "Sales Representative Solution",
    "url": "https://www.shl.com/products/product-catalog/view/sales-representative-solution/",
    "remote_testing": "",
    "adaptive_irt": "",
    "test_type": "A\nB\nP",
    "page_number": 11,
    "source": "SHL Catalog"
  },
  {
    "category": "Pre-packaged Job Solutions",
    "name": "Sales Supervisor Solution",
    "url": "https://www.shl.com/products/product-catalog/view/sales-supervisor-solution/",
    "remote_testing": "",
    "adaptive_irt": "",
    "test_type": "A\nB\nP",
    "page_number": 11,
    "source": "SHL Catalog"
  },
  {
    "category": "Pre-packaged Job Solutions",
    "name": "Sales Support Specialist Solution",
    "url": "https://www.shl.com/products/product-catalog/view/sales-support-specialist-solution/",
    "remote_testing": "",
    "adaptive_irt": "",
    "test_type": "A\nB\nP",
    "page_number": 11,
    "source": "SHL Catalog"
  },
  {
    "category": "Pre-packaged Job Solutions",
    "name": "Senior Insurance Agent Solution",
    "url": "https://www.shl.com/products/product-catalog/view/senior-insurance-agent-solution/",
    "remote_testing": "",
    "adaptive_irt": "",
    "test_type": "A\nB\nP",
    "page_number": 11,
    "source": "SHL Catalog"
  },
  {
    "category": "Pre-packaged Job Solutions",
    "name": "Senior Sales Professional Solution",
    "url": "https://www.shl.com/products/product-catalog/view/senior-sales-professional-solution/",
    "remote_testing": "",
    "adaptive_irt": "",
    "test_type": "A\nB\nP",
    "page_number": 11,
    "source": "SHL Catalog"
  },
  {
    "category": "Pre-packaged Job Solutions",
    "name": "Server Solution",
    "url": "https://www.shl.com/products/product-catalog/view/server-solution/",
    "remote_testing": "",
    "adaptive_irt": "",
    "test_type": "B\nA\nP",
    "page_number": 11,
    "source": "SHL Catalog"
  },
  {
    "category": "Pre-packaged Job Solutions",
    "name": "Service Associate Solution",
    "url": "https://www.shl.com/products/product-catalog/view/service-associate-solution/",
    "remote_testing": "",
    "adaptive_irt": "",
    "test_type": "A\nB\nP",
    "page_number": 11,
    "source": "SHL Catalog"
  },
  {
    "category": "Pre-packaged Job Solutions",
    "name": "Service Supervisor Solution",
    "url": "https://www.shl.com/products/product-catalog/view/service-supervisor-solution/",
    "remote_testing": "",
    "adaptive_irt": "",
    "test_type": "A\nB\nP",
    "page_number": 11,
    "source": "SHL Catalog"
  },
  {
    "category": "Pre-packaged Job Solutions",
    "name": "Stock Clerk Solution",
    "url": "https://www.shl.com/products/product-catalog/view/stock-clerk-solution/",
    "remote_testing": "",
    "adaptive_irt": "",
    "test_type": "A\nB\nP",
    "page_number": 11,
    "source": "SHL Catalog"
  },
  {
    "category": "Pre-packaged Job Solutions",
    "name": "Store Manager 7.0 Solution",
    "url": "https://www.shl.com/products/product-catalog/view/store-manager-7-0-solution/",
    "remote_testing": "",
    "adaptive_irt": "",
    "test_type": "B\nC",
    "page_number": 11,
    "source": "SHL Catalog"
  },
  {
    "category": "Pre-packaged Job Solutions",
    "name": "Store Manager 7.1 (Americas)",
    "url": "https://www.shl.com/products/product-catalog/view/store-manager-7-1-%28americas%29/",
    "remote_testing": "",
    "adaptive_irt": "",
    "test_type": "B\nC",
    "page_number": 11,
    "source": "SHL Catalog"
  },
  {
    "category": "Pre-packaged Job Solutions",
    "name": "Store Manager 7.1 (International)",
    "url": "https://www.shl.com/products/product-catalog/view/store-manager-7-1-%28international%29/",
    "remote_testing": "",
    "adaptive_irt": "",
    "test_type": "C\nB",
    "page_number": 12,
    "source": "SHL Catalog"
  },
  {
    "category": "Pre-packaged Job Solutions",
    "name": "Store Manager Solution",
    "url": "https://www.shl.com/products/product-catalog/view/store-manager-solution/",
    "remote_testing": "",
    "adaptive_irt": "",
    "test_type": "A\nB\nP",
    "page_number": 12,
    "source": "SHL Catalog"
  },
  {
    "category": "Pre-packaged Job Solutions",
    "name": "Supervisor - Short Form",
    "url": "https://www.shl.com/products/product-catalog/view/supervisor-short-form/",
    "remote_testing": "",
    "adaptive_irt": "",
    "test_type": "S",
    "page_number": 12,
    "source": "SHL Catalog"
  },
  {
    "category": "Pre-packaged Job Solutions",
    "name": "Supervisor 7.0 Solution",
    "url": "https://www.shl.com/products/product-catalog/view/supervisor-7-0-solution/",
    "remote_testing": "",
    "adaptive_irt": "",
    "test_type": "B\nC",
    "page_number": 12,
    "source": "SHL Catalog"
  },
  {
    "category": "Pre-packaged Job Solutions",
    "name": "Supervisor 7.1 (Americas)",
    "url": "https://www.shl.com/products/product-catalog/view/supervisor-7-1-%28americas%29/",
    "remote_testing": "",
    "adaptive_irt": "",
    "test_type": "B\nC\nP",
    "page_number": 12,
    "source": "SHL Catalog"
  },
  {
    "category": "Pre-packaged Job Solutions",
    "name": "Supervisor 7.1 (International)",
    "url": "https://www.shl.com/products/product-catalog/view/supervisor-7-1-%28international%29/",
    "remote_testing": "",
    "adaptive_irt": "",
    "test_type": "P\nC\nB",
    "page_number": 12,
    "source": "SHL Catalog"
  },
  {
    "category": "Pre-packaged Job Solutions",
    "name": "Support Associate Solution",
    "url": "https://www.shl.com/products/product-catalog/view/support-associate-solution/",
    "remote_testing": "",
    "adaptive_irt": "",
    "test_type": "A\nB\nP",
    "page_number": 12,
    "source": "SHL Catalog"
  },
  {
    "category": "Pre-packaged Job Solutions",
    "name": "Support Supervisor Solution",
    "url": "https://www.shl.com/products/product-catalog/view/support-supervisor-solution/",
    "remote_testing": "",
    "adaptive_irt": "",
    "test_type": "A\nP\nS\nB",
    "page_number": 12,
    "source": "SHL Catalog"
  },
  {
    "category": "Pre-packaged Job Solutions",
    "name": "Technical Sales Associate Solution",
    "url": "https://www.shl.com/products/product-catalog/view/technical-sales-associate-solution/",
    "remote_testing": "",
    "adaptive_irt": "",
    "test_type": "A\nB\nP",
    "page_number": 12,
    "source": "SHL Catalog"
  },
  {
    "category": "Pre-packaged Job Solutions",
    "name": "Technician/Technologist Solution",
    "url": "https://www.shl.com/products/product-catalog/view/techniciantechnologist-solution/",
    "remote_testing": "",
    "adaptive_irt": "",
    "test_type": "A\nB\nP",
    "page_number": 12,
    "source": "SHL Catalog"
  },
  {
    "category": "Pre-packaged Job Solutions",
    "name": "Technology Professional 8.0 Job Focused Assessment",
    "url": "https://www.shl.com/products/product-catalog/view/technology-professional-8-0-job-focused-assessment/",
    "remote_testing": "",
    "adaptive_irt": "",
    "test_type": "C\nP",
    "page_number": 12,
    "source": "SHL Catalog"
  },
  {
    "category": "Pre-packaged Job Solutions",
    "name": "Telenurse Solution",
    "url": "https://www.shl.com/products/product-catalog/view/telenurse-solution/",
    "remote_testing": "",
    "adaptive_irt": "",
    "test_type": "A\nB\nP",
    "page_number": 12,
    "source": "SHL Catalog"
  },
  {
    "category": "Pre-packaged Job Solutions",
    "name": "Teller 7.0",
    "url": "https://www.shl.com/products/product-catalog/view/teller-7-0/",
    "remote_testing": "",
    "adaptive_irt": "",
    "test_type": "B\nK\nP\nS",
    "page_number": 13,
    "source": "SHL Catalog"
  },
  {
    "category": "Pre-packaged Job Solutions",
    "name": "Teller with Sales - Short Form",
    "url": "https://www.shl.com/products/product-catalog/view/teller-with-sales-short-form/",
    "remote_testing": "",
    "adaptive_irt": "",
    "test_type": "A\nB\nK\nP\nS",
    "page_number": 13,
    "source": "SHL Catalog"
  },
  {
    "category": "Pre-packaged Job Solutions",
    "name": "Transcriptionist Solution",
    "url": "https://www.shl.com/products/product-catalog/view/transcriptionist-solution/",
    "remote_testing": "",
    "adaptive_irt": "",
    "test_type": "A\nB\nK\nP",
    "page_number": 13,
    "source": "SHL Catalog"
  },
  {
    "category": "Pre-packaged Job Solutions",
    "name": "Workplace Safety - Individual 7.0 Solution",
    "url": "https://www.shl.com/products/product-catalog/view/workplace-safety-individual-7-0-solution/",
    "remote_testing": "",
    "adaptive_irt": "",
    "test_type": "B",
    "page_number": 13,
    "source": "SHL Catalog"
  },
  {
    "category": "Pre-packaged Job Solutions",
    "name": "Workplace Safety - Individual 7.1 (Americas)",
    "url": "https://www.shl.com/products/product-catalog/view/workplace-safety-individual-7-1-solution/",
    "remote_testing": "",
    "adaptive_irt": "",
    "test_type": "B",
    "page_number": 13,
    "source": "SHL Catalog"
  },
  {
    "category": "Pre-packaged Job Solutions",
    "name": "Workplace Safety - Team 7.0 Solution",
    "url": "https://www.shl.com/products/product-catalog/view/workplace-safety-team-7-0-solution/",
    "remote_testing": "",
    "adaptive_irt": "",
    "test_type": "B",
    "page_number": 13,
    "source": "SHL Catalog"
  },
  {
    "category": "Pre-packaged Job Solutions",
    "name": "Workplace Safety - Team 7.1 (Americas)",
    "url": "https://www.shl.com/products/product-catalog/view/workplace-safety-team-7-1-%28americas%29/",
    "remote_testing": "",
    "adaptive_irt": "",
    "test_type": "B\nC\nP",
    "page_number": 13,
    "source": "SHL Catalog"
  },
  {
    "category": "Pre-packaged Job Solutions",
    "name": "Workplace Safety - Team 7.1 (International)",
    "url": "https://www.shl.com/products/product-catalog/view/workplace-safety-team-7-1-solution/",
    "remote_testing": "",
    "adaptive_irt": "",
    "test_type": "B\nC\nP",
    "page_number": 13,
    "source": "SHL Catalog"
  },
  {
    "category": "Pre-packaged Job Solutions",
    "name": "Workplace Safety Solution",
    "url": "https://www.shl.com/products/product-catalog/view/workplace-safety-solution/",
    "remote_testing": "",
    "adaptive_irt": "",
    "test_type": "B\nP",
    "page_number": 13,
    "source": "SHL Catalog"
  }
]